analytics/__init__.py
analytics/definitions.py
analytics/google.py
daily_ga_data/__init__.py
daily_ga_data/conf.py
daily_ga_data/definitions.py
daily_ga_data/main.py
daily_google_analytics_v3-0.1.dist-info/LICENSE
daily_google_analytics_v3-0.1.dist-info/METADATA
daily_google_analytics_v3-0.1.dist-info/WHEEL
daily_google_analytics_v3-0.1.dist-info/top_level.txt
daily_google_analytics_v3-0.1.dist-info/RECORD
